matflow_damask/__init__.py
matflow_damask/_version.py
matflow_damask/main.py
matflow_damask/utils.py
matflow_damask-0.1.29.dist-info/LICENSE
matflow_damask-0.1.29.dist-info/METADATA
matflow_damask-0.1.29.dist-info/WHEEL
matflow_damask-0.1.29.dist-info/entry_points.txt
matflow_damask-0.1.29.dist-info/top_level.txt
matflow_damask-0.1.29.dist-info/RECORD
