Metadata-Version: 2.1
Name: matflow-damask
Version: 0.1.29
Summary: Matflow extension for DAMASK.
Home-page: UNKNOWN
Author: Adam J. Plowman, Michael D. Atkinson, Guy L. P. Bowker
Author-email: adam.plowman@manchester.ac.uk
License: MIT license
Project-URL: GitHub, https://github.com/LightForm-group/matflow-damask
Keywords: matflow,materials-science,computational-workflow
Platform: UNKNOWN
Classifier: Development Status :: 4 - Beta
Classifier: Intended Audience :: Science/Research
Classifier: Topic :: Scientific/Engineering
Classifier: Operating System :: OS Independent
Classifier: License :: OSI Approved :: MIT License
Classifier: Natural Language :: English
Classifier: Programming Language :: Python :: 3
Classifier: Programming Language :: Python :: 3.6
Classifier: Programming Language :: Python :: 3.7
Classifier: Programming Language :: Python :: 3.8
Requires-Python: >=3.6
Requires-Dist: matflow
Requires-Dist: vtk
Requires-Dist: damask
Requires-Dist: damask-parse
